package_1/__init__.py
package_1/subpackage_1/__init__.py
package_1/subpackage_1/module_1.py
package_1/subpackage_2/__init__.py
package_1/subpackage_2/module_2.py
mapi_packaging_tutorial-1.2.3.dist-info/METADATA
mapi_packaging_tutorial-1.2.3.dist-info/WHEEL
mapi_packaging_tutorial-1.2.3.dist-info/top_level.txt
mapi_packaging_tutorial-1.2.3.dist-info/RECORD
